pathy/__init__.py
pathy/about.py
pathy/azure.py
pathy/cli.py
pathy/gcs.py
pathy/pathmod.py
pathy/py.typed
pathy/s3.py
pathy/_tests/__init__.py
pathy/_tests/conftest.py
pathy/_tests/test_azure.py
pathy/_tests/test_base.py
pathy/_tests/test_cli.py
pathy/_tests/test_clients.py
pathy/_tests/test_file.py
pathy/_tests/test_gcs.py
pathy/_tests/test_pathy.py
pathy/_tests/test_pathy_scandir.py
pathy/_tests/test_pure_pathy.py
pathy/_tests/test_s3.py
pathy/_tests/test_windows.py
pathy/_tests/fixtures/tar_but_not_gzipped.tar.gz
pathy-0.11.0.dist-info/LICENSE
pathy-0.11.0.dist-info/METADATA
pathy-0.11.0.dist-info/WHEEL
pathy-0.11.0.dist-info/entry_points.txt
pathy-0.11.0.dist-info/top_level.txt
pathy-0.11.0.dist-info/RECORD
