Metadata-Version: 2.1
Name: pathy
Version: 0.11.0
Summary: pathlib.Path subclasses for local and cloud bucket storage
Home-page: https://github.com/justindujardin/pathy
Author: Justin DuJardin
Author-email: justin@dujardinconsulting.com
License: Apache 2.0
Classifier: Development Status :: 4 - Beta
Classifier: Intended Audience :: Developers
Classifier: Natural Language :: English
Classifier: License :: OSI Approved :: Apache Software License
Classifier: Operating System :: OS Independent
Classifier: Programming Language :: Python
Classifier: Programming Language :: Python :: 3.8
Classifier: Programming Language :: Python :: 3.9
Classifier: Programming Language :: Python :: 3.10
Classifier: Programming Language :: Python :: 3.11
Classifier: Programming Language :: Python :: 3.12
Requires-Python: >= 3.8
License-File: LICENSE
Requires-Dist: smart-open<7.0.0,>=5.2.1
Requires-Dist: typer<1.0.0,>=0.3.0
Requires-Dist: dataclasses<1.0,>=0.6; python_version < "3.7"
Requires-Dist: pathlib_abc==0.1.1
Provides-Extra: gcs
Requires-Dist: google-cloud-storage<2.0.0,>=1.26.0; extra == "gcs"
Provides-Extra: s3
Requires-Dist: boto3; extra == "s3"
Provides-Extra: azure
Requires-Dist: azure-storage-blob; extra == "azure"
Provides-Extra: test
Requires-Dist: pytest; extra == "test"
Requires-Dist: pytest-coverage; extra == "test"
Requires-Dist: mock; extra == "test"
Requires-Dist: typer-cli; extra == "test"
Provides-Extra: all
Requires-Dist: google-cloud-storage<2.0.0,>=1.26.0; extra == "all"
Requires-Dist: boto3; extra == "all"
Requires-Dist: azure-storage-blob; extra == "all"
Requires-Dist: pytest; extra == "all"
Requires-Dist: pytest-coverage; extra == "all"
Requires-Dist: mock; extra == "all"
Requires-Dist: typer-cli; extra == "all"
